LICENSE
MANIFEST.in
README.rst
setup.cfg
setup.py
django_media_fixtures/__init__.py
django_media_fixtures/finders.py
django_media_fixtures/management/__init__.py
django_media_fixtures/management/commands/__init__.py
django_media_fixtures/management/commands/collectmedia.py
django_media_fixtures/tests/__init__.py
django_media_fixtures/tests/settings.py
django_media_fixtures/tests/testapp/__init__.py
django_media_fixtures/tests/testapp/apps.py
django_media_fixtures/tests/testapp/models.py
django_media_fixtures/tests/testapp/tests.py
django_media_fixtures_next.egg-info/PKG-INFO
django_media_fixtures_next.egg-info/SOURCES.txt
django_media_fixtures_next.egg-info/dependency_links.txt
django_media_fixtures_next.egg-info/entry_points.txt
django_media_fixtures_next.egg-info/not-zip-safe
django_media_fixtures_next.egg-info/requires.txt
django_media_fixtures_next.egg-info/top_level.txt