Metadata-Version: 2.1
Name: django-media-fixtures-next
Version: 1.0.1
Summary: Simple project to copy media files (intended for fixtures loads), pretty much as Django staticfiles does
Home-page: https://github.com/segidev/django-media-fixtures
Author: Adriano Veiga
Author-email: profpardal.88@gmail.com
License: MIT
Keywords: django collectmedia mediafiles mediafixtures fixtures media
Platform: UNKNOWN
Classifier: Development Status :: 5 - Production/Stable
Classifier: Intended Audience :: Developers
Classifier: Topic :: Software Development :: Libraries :: Python Modules
Classifier: Environment :: Web Environment
Classifier: Framework :: Django
Classifier: Framework :: Django :: 1.8
Classifier: Framework :: Django :: 1.11
Classifier: Framework :: Django :: 2.0
Classifier: Framework :: Django :: 2.2
Classifier: Framework :: Django :: 3.0
Classifier: License :: OSI Approved :: MIT License
Classifier: Programming Language :: Python :: 3
Classifier: Programming Language :: Python :: 3.5
Classifier: Programming Language :: Python :: 3.6
Classifier: Programming Language :: Python :: 3.7
Classifier: Programming Language :: Python :: 3.8
Classifier: Programming Language :: Python :: 3 :: Only
Requires-Python: >=3.5
Provides-Extra: dev
Provides-Extra: test
